iotp.py
iotp-1.0.2.1.dist-info/DESCRIPTION.rst
iotp-1.0.2.1.dist-info/entry_points.txt
iotp-1.0.2.1.dist-info/METADATA
iotp-1.0.2.1.dist-info/metadata.json
iotp-1.0.2.1.dist-info/RECORD
iotp-1.0.2.1.dist-info/top_level.txt
iotp-1.0.2.1.dist-info/WHEEL
