Metadata-Version: 2.0
Name: iotp
Version: 1.0.2.1
Summary: A CLI app for TOTP
Home-page: https://github.com/evilhamsterman/iotp
Author: Dan Mills
Author-email: UNKNOWN
License: Apache 2.0
Platform: UNKNOWN
Classifier: License :: OSI Approved :: Apache Software License
Classifier: Programming Language :: Python :: 2.7
Classifier: Programming Language :: Python :: 3
Classifier: Programming Language :: Python :: 3.0
Classifier: Programming Language :: Python :: 3.1
Classifier: Programming Language :: Python :: 3.2
Classifier: Programming Language :: Python :: 3.3
Classifier: Programming Language :: Python :: 3.4
Classifier: Programming Language :: Python :: 3.5
Classifier: Programming Language :: Python :: 3.6
Requires-Dist: click
Requires-Dist: pyotp
Requires-Dist: appdirs
Requires-Dist: pyperclip
